CHANGELOG.txt
LICENCE.txt
MANIFEST.in
README.txt
setup.py
sagetk/__init__.py
sagetk.egg-info/PKG-INFO
sagetk.egg-info/SOURCES.txt
sagetk.egg-info/dependency_links.txt
sagetk.egg-info/requires.txt
sagetk.egg-info/top_level.txt