Metadata-Version: 2.1
Name: sagetk
Version: 0.0.3
Summary: A Python library for creating GUIs in HTML/CSS like  syntax
Home-page: UNKNOWN
Author: Chanda Fungamwango Mark
Author-email: chandamark386@gmail.com
License: MIT
Keywords: sagetk,GUIs,html,gui,tkinter,tk
Platform: UNKNOWN
Classifier: Development Status :: 5 - Production/Stable
Classifier: Intended Audience :: Developers
Classifier: License :: OSI Approved :: MIT License
Classifier: Programming Language :: Python :: 3
Classifier: Programming Language :: Python :: 3.6
Classifier: Programming Language :: Python :: 3.7
Classifier: Programming Language :: Python :: 3.8
Classifier: Programming Language :: Python :: 3.9
Classifier: Programming Language :: Python :: 3.10
Classifier: Topic :: Software Development :: Libraries :: Python Modules
License-File: LICENCE.txt
